{
  "date": "2026-02-15",
  "decisions": [
    {
      "decision": "APPROVED",
      "proposal_id": "CTO-20260215-001",
      "reasoning": "Low-risk point upgrade with clear rollback path. Staying current on OpenClaw patches is good practice for stability and security. CTO provided proper verification steps.",
      "conditions": [
        "Must check release notes for breaking changes before updating",
        "Test with simple orchestrator task before declaring success",
        "Document any behavioral changes in learnings.md"
      ],
      "cascade_orders": [
        "Update company standard: Keep OpenClaw within 2 versions of latest",
        "DevOps agent: Add OpenClaw version monitoring to health checks"
      ],
      "priority": "next_sprint"
    }
  ]
}